CHANGELOG.rst
LICENSE.txt
MANIFEST.in
README.rst
TODO.txt
VERSION.txt
setup.cfg
setup.py
test-requirements.txt
pyramid_controllers/__init__.py
pyramid_controllers/adict.py
pyramid_controllers/controller.py
pyramid_controllers/decorator.py
pyramid_controllers/dispatcher.py
pyramid_controllers/integration.py
pyramid_controllers/restcontroller.py
pyramid_controllers/test_decorator.py
pyramid_controllers/test_dispatcher.py
pyramid_controllers/test_helpers.py
pyramid_controllers/test_restcontroller.py
pyramid_controllers/util.py
pyramid_controllers.egg-info/PKG-INFO
pyramid_controllers.egg-info/SOURCES.txt
pyramid_controllers.egg-info/dependency_links.txt
pyramid_controllers.egg-info/requires.txt
pyramid_controllers.egg-info/top_level.txt
pyramid_controllers.egg-info/zip-safe